sparepo/__init__.py
sparepo/accelerated.py
sparepo/build.py
sparepo/particle_types.py
sparepo/read.py
sparepo/regions.py
sparepo-0.3.0.dist-info/LICENSE
sparepo-0.3.0.dist-info/METADATA
sparepo-0.3.0.dist-info/WHEEL
sparepo-0.3.0.dist-info/top_level.txt
sparepo-0.3.0.dist-info/RECORD
