Metadata-Version: 2.1
Name: sparepo
Version: 0.3.0
Summary: Spatial loading for AREPO.
Home-page: https://github.com/jborrow/sparepo
Author: Josh Borrow
Author-email: josh@joshborrow.com
License: UNKNOWN
Platform: UNKNOWN
Classifier: Programming Language :: Python :: 3.8
Classifier: Programming Language :: Python :: 3.9
Classifier: License :: OSI Approved :: MIT License
Classifier: Operating System :: OS Independent
License-File: LICENSE
Requires-Dist: numba (>0.50.0)
Requires-Dist: attrs
Requires-Dist: h5py (>3.0.0)
Requires-Dist: numpy
